{
  "id": [
    "857469"
  ],
  "cjk_all": [
    "Science (Cambridge, Mass.)",
    "Science (Washington, D.C.)",
    "Science.",
    "Science magazine",
    "Cambridge, Mass. : M. King, 1883-",
    "v. : ill. ; 26-32 cm.",
    "Weekly (except last week in Dec.)",
    "[Vol. 1], no. 1 (Feb. 9, 1883)-v. 23, no. 581 (Mar. 23, 1894) ; new ser., v. 1, no. 1 (Jan. 4, 1895)-",
    "Since Jan. 1901, includes the official proceedings and most of the papers of the American Association for the Advancement of Science.",
    "Place of publication varies.",
    "Vols. for 1911-1913 contain: the Proceedings of the Helminthological Society of Washington, 1st-15th meeting.",
    "Title from caption.",
    "Science Periodicals.",
    "American Association for the Advancement of Science.",
    "Guide to scientific instruments 0533-5426",
    "AAAS observer Sept. 1988-Nov. 1989",
    "Helminthological Society of Washington. Proceedings of the Helminthological Society of Washington 0018-0130",
    "Science (New York, N.Y.) 0036-8075",
    "Scientific monthly Jan.1985 0096-3771",
    "Science express 4478078",
    "http:\/\/catalog.hathitrust.org\/Record\/008883092",
    "977093 f 1 Q1 .S3543",
    "977093 New ser., v. 23, no. 575 (Jan. 5, 1906)-v. 348, no. 6242 (June 26, 2015)",
    "977093 LACKS: no. 2221, 4421, 4488, 4526, 4986-88, 6227",
    "977093 CURRENT ISSUES IN: DeLong Room (RACK-PR). Firestone",
    "977093 DESIGNATOR: vol., no. (4 v.\/year)",
    "977094 rcppf 1 MICROFILM S01159 tr fr flm",
    "977094 [Vol. 1], no. 1 (Feb. 9, 1883)-v. 23, no. 581 (Mar. 23, 1894); new ser., v. 1, no. 1 (Jan. 4, 1895)-v. 22, no. 574 (Dec. 29, 1905)",
    "977094 Positive service microfilm",
    "977094 DESIGNATOR: vol., no.",
    "977094 replaces 87-S2529",
    "977095 pplps 1 Q1 .S35",
    "977095 Vol. 191, no. 4222 (1976)-v. 290, no. 5495 (17 Nov. 2000)",
    "977095 LACKS: no. 4307, 4350; v. 207-210; no. 4554, 4727-32, 4738, 4777-83, 4883-84, 5034-46, 5085-90, 5102, 5185, 5240, 5242, 5260  [may lack a few other early issues]",
    "977095 DESIGNATOR: vol., no.",
    "977096 sciss 8001.846",
    "977096 Vol. 3 (1884)-v. 7 (1886) ; new ser., v. 1, no. 1 (Jan. 4, 1895)-v. 352, no. 6285 (29 Apr. 2016)",
    "977096 LACKS: v. 139; v. 351, no. 6273-76",
    "977096 CURRENT ISSUES IN: Lewis Library (SCI)",
    "977096 DESIGNATOR: vol., no. (4 v.\/year) (1895-<1975> added by: new ser., v.; \"new ser.\" no longer used in later vols.)",
    "977097 rcppn 1 8001.846 tr fr smir",
    "977097 Vol. 91 (Jan. 1940)-v. 351, no. 6272 (29 Jan. 2016)",
    "977097 CURRENT ISSUES IN: Lewis Library (SCI)",
    "977097 DESIGNATOR: vol., no. (4 v.\/year)",
    "977099 spiaps 1 8001.846 withdrawn jeb 7\/2005",
    "977099 CURRENT YEAR ONLY IN: (SPIA)",
    "977101 stss 1 Q1 .S35",
    "977101 New ser., v. 215 (1982)-v. 335, no. 6076 (30 Mar. 2012)",
    "977101 LACKS: v. 292, no. 5501",
    "977101 CURRENT YEAR ISSUES ONLY",
    "977101 DESIGNATOR: vol., no. (4 v.\/year)",
    "977101 Bound holdings have been withdrawn. mwc",
    "977105 f 2 Q1 .S3543",
    "977105 COPY 2:  New ser., v. 23, no 575 (Jan. 5, 1906)-v. 166",
    "977105 LACKS: many issues in v. 23-110; v. 111-125; v. 128; v. 134-137;v. 139-142; v. 144-145; v. 146, no. ?; v. 147-163",
    "977105 DESIGNATOR: vol., no., c. 2",
    "977106 f 3 Q1 .S3543",
    "977106 COPY 3: Vol. 63, no. 1618-v. 90, no. 2348",
    "977106 DESIGNATOR: vol., no., c. 3",
    "3555490 rcppa 1 Q1 .S35 tr fr sz tr fr anxb",
    "3555490 Vol. 167 (1970)-v. 266, no. 2065 (23 Dec. 1994)",
    "3555490 LACKS: many earlier issues",
    "3555490 DESIGNATOR: vol., no.",
    "8684831 elf1 Electronic Resource"
  ],
  "author_citation_display": [
    "American Association for the Advancement of Science"
  ],
  "author_roles_1display": [
    "{\"secondary_authors\":[\"American Association for the Advancement of Science\"],\"translators\":[],\"editors\":[],\"compilers\":[]}"
  ],
  "author_s": [
    "American Association for the Advancement of Science"
  ],
  "uniform_title_s": [
    "Science (Cambridge, Mass.)"
  ],
  "title_display": [
    "Science."
  ],
  "title_sort": [
    "Science."
  ],
  "title_no_h_index": [
    "Science."
  ],
  "title_t": [
    "Science."
  ],
  "title_citation_display": [
    "Science."
  ],
  "compiled_created_t": [
    "Science."
  ],
  "pub_created_display": [
    "Cambridge, Mass. : M. King, 1883-"
  ],
  "pub_created_s": [
    "Cambridge, Mass. : M. King, 1883-"
  ],
  "pub_citation_display": [
    "Cambridge, Mass: M. King"
  ],
  "pub_date_display": [
    "1883"
  ],
  "pub_date_start_sort": [
    "1883"
  ],
  "pub_date_end_sort": [
    "9999"
  ],
  "cataloged_tdt": [
    "2000-06-08T04:00:00Z"
  ],
  "format": [
    "Journal"
  ],
  "electronic_access_1display": [
    "{\"http:\/\/catalog.hathitrust.org\/Record\/008883092\":[\"catalog.hathitrust.org\"]}"
  ],
  "description_display": [
    "v. : ill. ; 26-32 cm.",
    "[Vol. 1], no. 1 (Feb. 9, 1883)-v. 23, no. 581 (Mar. 23, 1894) ; new ser., v. 1, no. 1 (Jan. 4, 1895)-"
  ],
  "description_t": [
    "v. : ill. ; 26-32 cm.",
    "[Vol. 1], no. 1 (Feb. 9, 1883)-v. 23, no. 581 (Mar. 23, 1894) ; new ser., v. 1, no. 1 (Jan. 4, 1895)-"
  ],
  "issued_with_display": [
    "Helminthological Society of Washington. Proceedings of the Helminthological Society of Washington"
  ],
  "absorbed_display": [
    "Scientific monthly"
  ],
  "frequency_display": [
    "Weekly (except last week in Dec.)"
  ],
  "has_supplement_display": [
    "Guide to scientific instruments",
    "AAAS observer"
  ],
  "linking_notes_display": [
    "Vols. for 1911-1913 contain: the Proceedings of the Helminthological Society of Washington, 1st-15th meeting."
  ],
  "notes_display": [
    "Since Jan. 1901, includes the official proceedings and most of the papers of the American Association for the Advancement of Science.",
    "Place of publication varies."
  ],
  "source_desc_notes_display": [
    "Title from caption."
  ],
  "language_facet": [
    "English"
  ],
  "language_code_s": [
    "eng"
  ],
  "subject_display": [
    "Science\u2014Periodicals"
  ],
  "subject_facet": [
    "Science\u2014Periodicals"
  ],
  "subject_topic_facet": [
    "Science"
  ],
  "genre_facet": [
    "Periodicals"
  ],
  "related_name_json_1display": [
    "{\"Related name\":[\"American Association for the Advancement of Science\"]}"
  ],
  "other_title_index": [
    "Science (Washington, D.C.)",
    "Science magazine"
  ],
  "other_title_display": [
    "Science (Washington, D.C.)",
    "Science magazine"
  ],
  "issn_display": [
    "0036-8075"
  ],
  "lccn_display": [
    "   17024346 \/\/r862 "
  ],
  "lccn_s": [
    "17024346"
  ],
  "issn_s": [
    "00368075"
  ],
  "oclc_s": [
    "53849218"
  ],
  "standard_no_index": [
    "53849218",
    "NJPG94-S192",
    "857469"
  ],
  "other_version_s": [
    "00368075",
    "ocm53849218",
    "BIB4478078"
  ],
  "holdings_1display": [
    "{\"977093\":{\"location\":\"Firestone Library\",\"library\":\"Firestone Library\",\"location_code\":\"f\",\"call_number\":\"Q1 .S3543\",\"call_number_browse\":\"Q1 .S3543\",\"location_has\":[\"New ser., v. 23, no. 575 (Jan. 5, 1906)-v. 348, no. 6242 (June 26, 2015)\",\"LACKS: no. 2221, 4421, 4488, 4526, 4986-88, 6227\",\"CURRENT ISSUES IN: DeLong Room (RACK-PR). Firestone\"]},\"977094\":{\"location\":\"ReCAP - Use in Firestone Microforms only\",\"library\":\"ReCAP\",\"location_code\":\"rcppf\",\"call_number\":\"MICROFILM S01159\",\"call_number_browse\":\"MICROFILM S01159\",\"location_has\":[\"[Vol. 1], no. 1 (Feb. 9, 1883)-v. 23, no. 581 (Mar. 23, 1894); new ser., v. 1, no. 1 (Jan. 4, 1895)-v. 22, no. 574 (Dec. 29, 1905)\",\"Positive service microfilm\"]},\"977095\":{\"location\":\"Harold P. Furth Plasma Physics Library - Periodicals\",\"library\":\"Harold P. Furth Plasma Physics Library\",\"location_code\":\"pplps\",\"call_number\":\"Q1 .S35\",\"call_number_browse\":\"Q1 .S35\",\"location_has\":[\"Vol. 191, no. 4222 (1976)-v. 290, no. 5495 (17 Nov. 2000)\",\"LACKS: no. 4307, 4350; v. 207-210; no. 4554, 4727-32, 4738, 4777-83, 4883-84, 5034-46, 5085-90, 5102, 5185, 5240, 5242, 5260  [may lack a few other early issues]\"]},\"977096\":{\"location\":\"Lewis Library - Serials (shelved by serial title)\",\"library\":\"Lewis Library\",\"location_code\":\"sciss\",\"call_number\":\"8001.846\",\"call_number_browse\":\"8001.846\",\"location_has\":[\"Vol. 3 (1884)-v. 7 (1886) ; new ser., v. 1, no. 1 (Jan. 4, 1895)-v. 352, no. 6285 (29 Apr. 2016)\",\"LACKS: v. 139; v. 351, no. 6273-76\",\"CURRENT ISSUES IN: Lewis Library (SCI)\"]},\"977097\":{\"location\":\"ReCAP - Lewis Library use only\",\"library\":\"ReCAP\",\"location_code\":\"rcppn\",\"call_number\":\"8001.846\",\"call_number_browse\":\"8001.846\",\"location_has\":[\"Vol. 91 (Jan. 1940)-v. 351, no. 6272 (29 Jan. 2016)\",\"CURRENT ISSUES IN: Lewis Library (SCI)\"]},\"977099\":{\"location\":\"Stokes Library - Periodicals\",\"library\":\"Stokes Library\",\"location_code\":\"spiaps\",\"call_number\":\"8001.846\",\"call_number_browse\":\"8001.846\",\"location_has\":[\"CURRENT YEAR ONLY IN: (SPIA)\"]},\"977101\":{\"location\":\"Engineering Library - Serials\",\"library\":\"Engineering Library\",\"location_code\":\"stss\",\"call_number\":\"Q1 .S35\",\"call_number_browse\":\"Q1 .S35\",\"location_has\":[\"CURRENT YEAR ISSUES ONLY\"]},\"977105\":{\"location\":\"Firestone Library\",\"library\":\"Firestone Library\",\"location_code\":\"f\",\"call_number\":\"Q1 .S3543\",\"call_number_browse\":\"Q1 .S3543\",\"location_has\":[\"COPY 2:  New ser., v. 23, no 575 (Jan. 5, 1906)-v. 166\",\"LACKS: many issues in v. 23-110; v. 111-125; v. 128; v. 134-137;v. 139-142; v. 144-145; v. 146, no. ?; v. 147-163\"]},\"977106\":{\"location\":\"Firestone Library\",\"library\":\"Firestone Library\",\"location_code\":\"f\",\"call_number\":\"Q1 .S3543\",\"call_number_browse\":\"Q1 .S3543\",\"location_has\":[\"COPY 3: Vol. 63, no. 1618-v. 90, no. 2348\"]},\"3555490\":{\"location\":\"ReCAP\",\"library\":\"ReCAP\",\"location_code\":\"rcppa\",\"call_number\":\"Q1 .S35\",\"call_number_browse\":\"Q1 .S35\",\"location_has\":[\"Vol. 167 (1970)-v. 266, no. 2065 (23 Dec. 1994)\",\"LACKS: many earlier issues\"]},\"8684831\":{\"location\":\"Online - *ONLINE*\",\"library\":\"Online\",\"location_code\":\"elf1\",\"call_number\":\"Electronic Resource\",\"call_number_browse\":\"Electronic Resource\"}}"
  ],
  "location_code_s": [
    "f",
    "rcppf",
    "pplps",
    "sciss",
    "rcppn",
    "spiaps",
    "stss",
    "rcppa",
    "elf1"
  ],
  "location_display": [
    "Firestone Library",
    "ReCAP - Use in Firestone Microforms only",
    "Harold P. Furth Plasma Physics Library - Periodicals",
    "Lewis Library - Serials (shelved by serial title)",
    "ReCAP - Lewis Library use only",
    "Stokes Library - Periodicals",
    "Engineering Library - Serials",
    "ReCAP",
    "Online - *ONLINE*"
  ],
  "location": [
    "Firestone Library",
    "ReCAP",
    "Harold P. Furth Plasma Physics Library",
    "Lewis Library",
    "ReCAP",
    "Stokes Library",
    "Engineering Library",
    "ReCAP"
  ],
  "access_facet": [
    "In the Library",
    "In the Library",
    "In the Library",
    "In the Library",
    "In the Library",
    "In the Library",
    "In the Library",
    "In the Library",
    "Online"
  ],
  "call_number_display": [
    "Q1 .S3543",
    "MICROFILM S01159",
    "Q1 .S35",
    "8001.846",
    "8001.846",
    "8001.846",
    "Q1 .S35",
    "Q1 .S3543",
    "Q1 .S3543",
    "Q1 .S35",
    "Electronic Resource"
  ],
  "call_number_browse_s": [
    "Q1 .S3543",
    "MICROFILM S01159",
    "Q1 .S35",
    "8001.846",
    "Electronic Resource"
  ]
}
