[
{"id": 1, "cjk_mapped_from": "両", "cjk_mapped_to": "兩"},
{"id": 2, "cjk_mapped_from": "並", "cjk_mapped_to": "竝"},
{"id": 3, "cjk_mapped_from": "乗", "cjk_mapped_to": "乘"},
{"id": 4, "cjk_mapped_from": "予", "cjk_mapped_to": "豫"},
{"id": 5, "cjk_mapped_from": "亜", "cjk_mapped_to": "亞"},
{"id": 6, "cjk_mapped_from": "価", "cjk_mapped_to": "價"},
{"id": 7, "cjk_mapped_from": "仏", "cjk_mapped_to": "佛"},
{"id": 8, "cjk_mapped_from": "仮", "cjk_mapped_to": "假"},
{"id": 9, "cjk_mapped_from": "伝", "cjk_mapped_to": "傳"},
{"id": 10, "cjk_mapped_from": "併", "cjk_mapped_to": "倂"},
{"id": 11, "cjk_mapped_from": "侮", "cjk_mapped_to": "侮"},
{"id": 12, "cjk_mapped_from": "倹", "cjk_mapped_to": "儉"},
{"id": 13, "cjk_mapped_from": "偽", "cjk_mapped_to": "僞"},
{"id": 14, "cjk_mapped_from": "免", "cjk_mapped_to": "免"},
{"id": 15, "cjk_mapped_from": "児", "cjk_mapped_to": "兒"},
{"id": 16, "cjk_mapped_from": "円", "cjk_mapped_to": "圓"},
{"id": 17, "cjk_mapped_from": "処", "cjk_mapped_to": "處"},
{"id": 18, "cjk_mapped_from": "刊", "cjk_mapped_to": "刋"},
{"id": 19, "cjk_mapped_from": "剣", "cjk_mapped_to": "劍"},
{"id": 20, "cjk_mapped_from": "剤", "cjk_mapped_to": "劑"},
{"id": 21, "cjk_mapped_from": "剰", "cjk_mapped_to": "剩"},
{"id": 22, "cjk_mapped_from": "励", "cjk_mapped_to": "勵"},
{"id": 23, "cjk_mapped_from": "労", "cjk_mapped_to": "勞"},
{"id": 24, "cjk_mapped_from": "効", "cjk_mapped_to": "效"},
{"id": 25, "cjk_mapped_from": "勉", "cjk_mapped_to": "勉"},
{"id": 26, "cjk_mapped_from": "勤", "cjk_mapped_to": "勤"},
{"id": 27, "cjk_mapped_from": "勧", "cjk_mapped_to": "勸"},
{"id": 28, "cjk_mapped_from": "勲", "cjk_mapped_to": "勳"},
{"id": 29, "cjk_mapped_from": "卑", "cjk_mapped_to": "卑"},
{"id": 30, "cjk_mapped_from": "単", "cjk_mapped_to": "單"},
{"id": 31, "cjk_mapped_from": "即", "cjk_mapped_to": "卽"},
{"id": 32, "cjk_mapped_from": "厳", "cjk_mapped_to": "嚴"},
{"id": 33, "cjk_mapped_from": "収", "cjk_mapped_to": "收"},
{"id": 34, "cjk_mapped_from": "叙", "cjk_mapped_to": "敍"},
{"id": 35, "cjk_mapped_from": "喝", "cjk_mapped_to": "喝"},
{"id": 36, "cjk_mapped_from": "営", "cjk_mapped_to": "營"},
{"id": 37, "cjk_mapped_from": "嘆", "cjk_mapped_to": "嘆"},
{"id": 38, "cjk_mapped_from": "器", "cjk_mapped_to": "器"},
{"id": 39, "cjk_mapped_from": "団", "cjk_mapped_to": "團"},
{"id": 40, "cjk_mapped_from": "囯", "cjk_mapped_to": "國"},
{"id": 41, "cjk_mapped_from": "囲", "cjk_mapped_to": "圍"},
{"id": 42, "cjk_mapped_from": "図", "cjk_mapped_to": "圖"},
{"id": 43, "cjk_mapped_from": "圏", "cjk_mapped_to": "圈"},
{"id": 44, "cjk_mapped_from": "圧", "cjk_mapped_to": "壓"},
{"id": 45, "cjk_mapped_from": "塀", "cjk_mapped_to": "塀"},
{"id": 46, "cjk_mapped_from": "塁", "cjk_mapped_to": "壘"},
{"id": 47, "cjk_mapped_from": "塚", "cjk_mapped_to": "塚"},
{"id": 48, "cjk_mapped_from": "塩", "cjk_mapped_to": "鹽"},
{"id": 49, "cjk_mapped_from": "増", "cjk_mapped_to": "增"},
{"id": 50, "cjk_mapped_from": "墨", "cjk_mapped_to": "墨"},
{"id": 51, "cjk_mapped_from": "壊", "cjk_mapped_to": "壞"},
{"id": 52, "cjk_mapped_from": "壌", "cjk_mapped_to": "壤"},
{"id": 53, "cjk_mapped_from": "壱", "cjk_mapped_to": "壹"},
{"id": 54, "cjk_mapped_from": "売", "cjk_mapped_to": "賣"},
{"id": 55, "cjk_mapped_from": "変", "cjk_mapped_to": "變"},
{"id": 56, "cjk_mapped_from": "奥", "cjk_mapped_to": "奧"},
{"id": 57, "cjk_mapped_from": "奨", "cjk_mapped_to": "奬"},
{"id": 58, "cjk_mapped_from": "姫", "cjk_mapped_to": "姬"},
{"id": 59, "cjk_mapped_from": "嬢", "cjk_mapped_to": "孃"},
{"id": 60, "cjk_mapped_from": "実", "cjk_mapped_to": "實"},
{"id": 61, "cjk_mapped_from": "寛", "cjk_mapped_to": "寬"},
{"id": 62, "cjk_mapped_from": "対", "cjk_mapped_to": "對"},
{"id": 63, "cjk_mapped_from": "専", "cjk_mapped_to": "專"},
{"id": 64, "cjk_mapped_from": "届", "cjk_mapped_to": "屆"},
{"id": 65, "cjk_mapped_from": "層", "cjk_mapped_to": "層"},
{"id": 66, "cjk_mapped_from": "嶽", "cjk_mapped_to": "岳"},
{"id": 67, "cjk_mapped_from": "州", "cjk_mapped_to": "洲"},
{"id": 68, "cjk_mapped_from": "巣", "cjk_mapped_to": "巢"},
{"id": 69, "cjk_mapped_from": "巻", "cjk_mapped_to": "卷"},
{"id": 70, "cjk_mapped_from": "帯", "cjk_mapped_to": "帶"},
{"id": 71, "cjk_mapped_from": "帰", "cjk_mapped_to": "歸"},
{"id": 72, "cjk_mapped_from": "庁", "cjk_mapped_to": "廳"},
{"id": 73, "cjk_mapped_from": "広", "cjk_mapped_to": "廣"},
{"id": 74, "cjk_mapped_from": "廃", "cjk_mapped_to": "廢"},
{"id": 75, "cjk_mapped_from": "廊", "cjk_mapped_to": "廊"},
{"id": 76, "cjk_mapped_from": "弐", "cjk_mapped_to": "貳"},
{"id": 77, "cjk_mapped_from": "弾", "cjk_mapped_to": "彈"},
{"id": 78, "cjk_mapped_from": "従", "cjk_mapped_to": "從"},
{"id": 79, "cjk_mapped_from": "徳", "cjk_mapped_to": "德"},
{"id": 80, "cjk_mapped_from": "徴", "cjk_mapped_to": "徵"},
{"id": 81, "cjk_mapped_from": "応", "cjk_mapped_to": "應"},
{"id": 82, "cjk_mapped_from": "恋", "cjk_mapped_to": "戀"},
{"id": 83, "cjk_mapped_from": "恒", "cjk_mapped_to": "恆"},
{"id": 84, "cjk_mapped_from": "恵", "cjk_mapped_to": "惠"},
{"id": 85, "cjk_mapped_from": "悔", "cjk_mapped_to": "悔"},
{"id": 86, "cjk_mapped_from": "悩", "cjk_mapped_to": "惱"},
{"id": 87, "cjk_mapped_from": "悪", "cjk_mapped_to": "惡"},
{"id": 88, "cjk_mapped_from": "慨", "cjk_mapped_to": "慨"},
{"id": 89, "cjk_mapped_from": "憎", "cjk_mapped_to": "憎"},
{"id": 90, "cjk_mapped_from": "懐", "cjk_mapped_to": "懷"},
{"id": 91, "cjk_mapped_from": "懲", "cjk_mapped_to": "懲"},
{"id": 92, "cjk_mapped_from": "戦", "cjk_mapped_to": "戰"},
{"id": 93, "cjk_mapped_from": "戱", "cjk_mapped_to": "戲"},
{"id": 94, "cjk_mapped_from": "戯", "cjk_mapped_to": "戲"},
{"id": 95, "cjk_mapped_from": "戸", "cjk_mapped_to": "戶"},
{"id": 96, "cjk_mapped_from": "戻", "cjk_mapped_to": "戾"},
{"id": 97, "cjk_mapped_from": "払", "cjk_mapped_to": "拂"},
{"id": 98, "cjk_mapped_from": "抜", "cjk_mapped_to": "拔"},
{"id": 99, "cjk_mapped_from": "択", "cjk_mapped_to": "擇"},
{"id": 100, "cjk_mapped_from": "拝", "cjk_mapped_to": "拜"},
{"id": 101, "cjk_mapped_from": "拠", "cjk_mapped_to": "據"},
{"id": 102, "cjk_mapped_from": "拡", "cjk_mapped_to": "擴"},
{"id": 103, "cjk_mapped_from": "挙", "cjk_mapped_to": "擧"},
{"id": 104, "cjk_mapped_from": "挿", "cjk_mapped_to": "插"},
{"id": 105, "cjk_mapped_from": "捜", "cjk_mapped_to": "搜"},
{"id": 106, "cjk_mapped_from": "掲", "cjk_mapped_to": "揭"},
{"id": 107, "cjk_mapped_from": "揺", "cjk_mapped_to": "搖"},
{"id": 108, "cjk_mapped_from": "摂", "cjk_mapped_to": "攝"},
{"id": 109, "cjk_mapped_from": "撃", "cjk_mapped_to": "擊"},
{"id": 110, "cjk_mapped_from": "敎", "cjk_mapped_to": "教"},
{"id": 111, "cjk_mapped_from": "敏", "cjk_mapped_to": "敏"},
{"id": 112, "cjk_mapped_from": "斉", "cjk_mapped_to": "齊"},
{"id": 113, "cjk_mapped_from": "斎", "cjk_mapped_to": "齋"},
{"id": 114, "cjk_mapped_from": "既", "cjk_mapped_to": "旣"},
{"id": 115, "cjk_mapped_from": "晩", "cjk_mapped_to": "晚"},
{"id": 116, "cjk_mapped_from": "暁", "cjk_mapped_to": "曉"},
{"id": 117, "cjk_mapped_from": "暑", "cjk_mapped_to": "暑"},
{"id": 118, "cjk_mapped_from": "暦", "cjk_mapped_to": "曆"},
{"id": 119, "cjk_mapped_from": "朗", "cjk_mapped_to": "朗"},
{"id": 120, "cjk_mapped_from": "査", "cjk_mapped_to": "查"},
{"id": 121, "cjk_mapped_from": "栄", "cjk_mapped_to": "榮"},
{"id": 122, "cjk_mapped_from": "桜", "cjk_mapped_to": "櫻"},
{"id": 123, "cjk_mapped_from": "桟", "cjk_mapped_to": "棧"},
{"id": 124, "cjk_mapped_from": "梅", "cjk_mapped_to": "梅"},
{"id": 125, "cjk_mapped_from": "検", "cjk_mapped_to": "檢"},
{"id": 126, "cjk_mapped_from": "楽", "cjk_mapped_to": "樂"},
{"id": 127, "cjk_mapped_from": "様", "cjk_mapped_to": "樣"},
{"id": 128, "cjk_mapped_from": "権", "cjk_mapped_to": "權"},
{"id": 129, "cjk_mapped_from": "横", "cjk_mapped_to": "橫"},
{"id": 130, "cjk_mapped_from": "欄", "cjk_mapped_to": "欄"},
{"id": 131, "cjk_mapped_from": "欠", "cjk_mapped_to": "缺"},
{"id": 132, "cjk_mapped_from": "歓", "cjk_mapped_to": "歡"},
{"id": 133, "cjk_mapped_from": "歩", "cjk_mapped_to": "步"},
{"id": 134, "cjk_mapped_from": "歯", "cjk_mapped_to": "齒"},
{"id": 135, "cjk_mapped_from": "歴", "cjk_mapped_to": "歷"},
{"id": 136, "cjk_mapped_from": "残", "cjk_mapped_to": "殘"},
{"id": 137, "cjk_mapped_from": "殺", "cjk_mapped_to": "殺"},
{"id": 138, "cjk_mapped_from": "殻", "cjk_mapped_to": "殼"},
{"id": 139, "cjk_mapped_from": "毎", "cjk_mapped_to": "每"},
{"id": 140, "cjk_mapped_from": "気", "cjk_mapped_to": "氣"},
{"id": 141, "cjk_mapped_from": "沢", "cjk_mapped_to": "澤"},
{"id": 142, "cjk_mapped_from": "浜", "cjk_mapped_to": "濱"},
{"id": 143, "cjk_mapped_from": "海", "cjk_mapped_to": "海"},
{"id": 144, "cjk_mapped_from": "涙", "cjk_mapped_to": "淚"},
{"id": 145, "cjk_mapped_from": "渇", "cjk_mapped_to": "渴"},
{"id": 146, "cjk_mapped_from": "済", "cjk_mapped_to": "濟"},
{"id": 147, "cjk_mapped_from": "渉", "cjk_mapped_to": "涉"},
{"id": 148, "cjk_mapped_from": "渋", "cjk_mapped_to": "澁"},
{"id": 149, "cjk_mapped_from": "渓", "cjk_mapped_to": "溪"},
{"id": 150, "cjk_mapped_from": "温", "cjk_mapped_to": "溫"},
{"id": 151, "cjk_mapped_from": "湿", "cjk_mapped_to": "濕"},
{"id": 152, "cjk_mapped_from": "満", "cjk_mapped_to": "滿"},
{"id": 153, "cjk_mapped_from": "滝", "cjk_mapped_to": "瀧"},
{"id": 154, "cjk_mapped_from": "滞", "cjk_mapped_to": "滯"},
{"id": 155, "cjk_mapped_from": "漢", "cjk_mapped_to": "漢"},
{"id": 156, "cjk_mapped_from": "瀬", "cjk_mapped_to": "瀨"},
{"id": 157, "cjk_mapped_from": "焼", "cjk_mapped_to": "燒"},
{"id": 158, "cjk_mapped_from": "煮", "cjk_mapped_to": "煮"},
{"id": 159, "cjk_mapped_from": "犠", "cjk_mapped_to": "犧"},
{"id": 160, "cjk_mapped_from": "猟", "cjk_mapped_to": "獵"},
{"id": 161, "cjk_mapped_from": "獣", "cjk_mapped_to": "獸"},
{"id": 162, "cjk_mapped_from": "瓶", "cjk_mapped_to": "甁"},
{"id": 163, "cjk_mapped_from": "甯", "cjk_mapped_to": "寧"},
{"id": 164, "cjk_mapped_from": "画", "cjk_mapped_to": "畫"},
{"id": 165, "cjk_mapped_from": "畳", "cjk_mapped_to": "疊"},
{"id": 166, "cjk_mapped_from": "発", "cjk_mapped_to": "發"},
{"id": 167, "cjk_mapped_from": "県", "cjk_mapped_to": "縣"},
{"id": 168, "cjk_mapped_from": "砕", "cjk_mapped_to": "碎"},
{"id": 169, "cjk_mapped_from": "硏", "cjk_mapped_to": "研"},
{"id": 170, "cjk_mapped_from": "碑", "cjk_mapped_to": "碑"},
{"id": 171, "cjk_mapped_from": "祉", "cjk_mapped_to": "祉"},
{"id": 172, "cjk_mapped_from": "祥", "cjk_mapped_to": "祥"},
{"id": 173, "cjk_mapped_from": "禍", "cjk_mapped_to": "禍"},
{"id": 174, "cjk_mapped_from": "福", "cjk_mapped_to": "福"},
{"id": 175, "cjk_mapped_from": "秘", "cjk_mapped_to": "祕"},
{"id": 176, "cjk_mapped_from": "稲", "cjk_mapped_to": "稻"},
{"id": 177, "cjk_mapped_from": "穀", "cjk_mapped_to": "穀"},
{"id": 178, "cjk_mapped_from": "穂", "cjk_mapped_to": "穗"},
{"id": 179, "cjk_mapped_from": "穏", "cjk_mapped_to": "穩"},
{"id": 180, "cjk_mapped_from": "突", "cjk_mapped_to": "突"},
{"id": 181, "cjk_mapped_from": "竜", "cjk_mapped_to": "龍"},
{"id": 182, "cjk_mapped_from": "節", "cjk_mapped_to": "節"},
{"id": 183, "cjk_mapped_from": "粋", "cjk_mapped_to": "粹"},
{"id": 184, "cjk_mapped_from": "粛", "cjk_mapped_to": "肅"},
{"id": 185, "cjk_mapped_from": "糸", "cjk_mapped_to": "絲"},
{"id": 186, "cjk_mapped_from": "経", "cjk_mapped_to": "經"},
{"id": 187, "cjk_mapped_from": "絵", "cjk_mapped_to": "繪"},
{"id": 188, "cjk_mapped_from": "継", "cjk_mapped_to": "繼"},
{"id": 189, "cjk_mapped_from": "続", "cjk_mapped_to": "續"},
{"id": 190, "cjk_mapped_from": "総", "cjk_mapped_to": "總"},
{"id": 191, "cjk_mapped_from": "緑", "cjk_mapped_to": "綠"},
{"id": 192, "cjk_mapped_from": "緖", "cjk_mapped_to": "緒"},
{"id": 193, "cjk_mapped_from": "練", "cjk_mapped_to": "練"},
{"id": 194, "cjk_mapped_from": "縁", "cjk_mapped_to": "緣"},
{"id": 195, "cjk_mapped_from": "縄", "cjk_mapped_to": "繩"},
{"id": 196, "cjk_mapped_from": "縦", "cjk_mapped_to": "縱"},
{"id": 197, "cjk_mapped_from": "繁", "cjk_mapped_to": "繁"},
{"id": 198, "cjk_mapped_from": "繊", "cjk_mapped_to": "纖"},
{"id": 199, "cjk_mapped_from": "缶", "cjk_mapped_to": "罐"},
{"id": 200, "cjk_mapped_from": "署", "cjk_mapped_to": "署"},
{"id": 201, "cjk_mapped_from": "翻", "cjk_mapped_to": "飜"},
{"id": 202, "cjk_mapped_from": "者", "cjk_mapped_to": "者"},
{"id": 203, "cjk_mapped_from": "聴", "cjk_mapped_to": "聽"},
{"id": 204, "cjk_mapped_from": "脳", "cjk_mapped_to": "腦"},
{"id": 205, "cjk_mapped_from": "臓", "cjk_mapped_to": "臟"},
{"id": 206, "cjk_mapped_from": "臭", "cjk_mapped_to": "臭"},
{"id": 207, "cjk_mapped_from": "芸", "cjk_mapped_to": "藝"},
{"id": 208, "cjk_mapped_from": "荘", "cjk_mapped_to": "莊"},
{"id": 209, "cjk_mapped_from": "著", "cjk_mapped_to": "著"},
{"id": 210, "cjk_mapped_from": "蔵", "cjk_mapped_to": "藏"},
{"id": 211, "cjk_mapped_from": "薫", "cjk_mapped_to": "薰"},
{"id": 212, "cjk_mapped_from": "薬", "cjk_mapped_to": "藥"},
{"id": 213, "cjk_mapped_from": "虚", "cjk_mapped_to": "虛"},
{"id": 214, "cjk_mapped_from": "虜", "cjk_mapped_to": "虜"},
{"id": 215, "cjk_mapped_from": "蛍", "cjk_mapped_to": "螢"},
{"id": 216, "cjk_mapped_from": "蛮", "cjk_mapped_to": "蠻"},
{"id": 217, "cjk_mapped_from": "衛", "cjk_mapped_to": "衞"},
{"id": 218, "cjk_mapped_from": "褐", "cjk_mapped_to": "褐"},
{"id": 219, "cjk_mapped_from": "褒", "cjk_mapped_to": "襃"},
{"id": 220, "cjk_mapped_from": "覇", "cjk_mapped_to": "霸"},
{"id": 221, "cjk_mapped_from": "視", "cjk_mapped_to": "視"},
{"id": 222, "cjk_mapped_from": "覚", "cjk_mapped_to": "覺"},
{"id": 223, "cjk_mapped_from": "覧", "cjk_mapped_to": "覽"},
{"id": 224, "cjk_mapped_from": "観", "cjk_mapped_to": "觀"},
{"id": 225, "cjk_mapped_from": "訳", "cjk_mapped_to": "譯"},
{"id": 226, "cjk_mapped_from": "証", "cjk_mapped_to": "證"},
{"id": 227, "cjk_mapped_from": "誉", "cjk_mapped_to": "譽"},
{"id": 228, "cjk_mapped_from": "読", "cjk_mapped_to": "讀"},
{"id": 229, "cjk_mapped_from": "諸", "cjk_mapped_to": "諸"},
{"id": 230, "cjk_mapped_from": "謁", "cjk_mapped_to": "謁"},
{"id": 231, "cjk_mapped_from": "謡", "cjk_mapped_to": "謠"},
{"id": 232, "cjk_mapped_from": "謹", "cjk_mapped_to": "謹"},
{"id": 233, "cjk_mapped_from": "譲", "cjk_mapped_to": "讓"},
{"id": 234, "cjk_mapped_from": "豊", "cjk_mapped_to": "豐"},
{"id": 235, "cjk_mapped_from": "賓", "cjk_mapped_to": "賓"},
{"id": 236, "cjk_mapped_from": "賛", "cjk_mapped_to": "贊"},
{"id": 237, "cjk_mapped_from": "贈", "cjk_mapped_to": "贈"},
{"id": 238, "cjk_mapped_from": "転", "cjk_mapped_to": "轉"},
{"id": 239, "cjk_mapped_from": "軽", "cjk_mapped_to": "輕"},
{"id": 240, "cjk_mapped_from": "辺", "cjk_mapped_to": "邊"},
{"id": 241, "cjk_mapped_from": "逓", "cjk_mapped_to": "遞"},
{"id": 242, "cjk_mapped_from": "逸", "cjk_mapped_to": "逸"},
{"id": 243, "cjk_mapped_from": "遅", "cjk_mapped_to": "遲"},
{"id": 244, "cjk_mapped_from": "郎", "cjk_mapped_to": "郞"},
{"id": 245, "cjk_mapped_from": "郷", "cjk_mapped_to": "鄕"},
{"id": 246, "cjk_mapped_from": "都", "cjk_mapped_to": "都"},
{"id": 247, "cjk_mapped_from": "酔", "cjk_mapped_to": "醉"},
{"id": 248, "cjk_mapped_from": "醸", "cjk_mapped_to": "釀"},
{"id": 249, "cjk_mapped_from": "釈", "cjk_mapped_to": "釋"},
{"id": 250, "cjk_mapped_from": "鉄", "cjk_mapped_to": "鐵"},
{"id": 251, "cjk_mapped_from": "鉱", "cjk_mapped_to": "鑛"},
{"id": 252, "cjk_mapped_from": "銭", "cjk_mapped_to": "錢"},
{"id": 253, "cjk_mapped_from": "錬", "cjk_mapped_to": "鍊"},
{"id": 254, "cjk_mapped_from": "録", "cjk_mapped_to": "錄"},
{"id": 255, "cjk_mapped_from": "鎮", "cjk_mapped_to": "鎭"},
{"id": 256, "cjk_mapped_from": "関", "cjk_mapped_to": "關"},
{"id": 257, "cjk_mapped_from": "闘", "cjk_mapped_to": "鬪"},
{"id": 258, "cjk_mapped_from": "陥", "cjk_mapped_to": "陷"},
{"id": 259, "cjk_mapped_from": "険", "cjk_mapped_to": "險"},
{"id": 260, "cjk_mapped_from": "隆", "cjk_mapped_to": "隆"},
{"id": 261, "cjk_mapped_from": "隠", "cjk_mapped_to": "隱"},
{"id": 262, "cjk_mapped_from": "雑", "cjk_mapped_to": "雜"},
{"id": 263, "cjk_mapped_from": "難", "cjk_mapped_to": "難"},
{"id": 264, "cjk_mapped_from": "霊", "cjk_mapped_to": "靈"},
{"id": 265, "cjk_mapped_from": "響", "cjk_mapped_to": "響"},
{"id": 266, "cjk_mapped_from": "頻", "cjk_mapped_to": "頻"},
{"id": 267, "cjk_mapped_from": "頼", "cjk_mapped_to": "賴"},
{"id": 268, "cjk_mapped_from": "顕", "cjk_mapped_to": "顯"},
{"id": 269, "cjk_mapped_from": "類", "cjk_mapped_to": "類"},
{"id": 270, "cjk_mapped_from": "駅", "cjk_mapped_to": "驛"},
{"id": 271, "cjk_mapped_from": "駆", "cjk_mapped_to": "驅"},
{"id": 272, "cjk_mapped_from": "騒", "cjk_mapped_to": "騷"},
{"id": 273, "cjk_mapped_from": "験", "cjk_mapped_to": "驗"},
{"id": 274, "cjk_mapped_from": "髪", "cjk_mapped_to": "髮"},
{"id": 275, "cjk_mapped_from": "鶏", "cjk_mapped_to": "鷄"},
{"id": 276, "cjk_mapped_from": "麦", "cjk_mapped_to": "麥"},
{"id": 277, "cjk_mapped_from": "黄", "cjk_mapped_to": "黃"},
{"id": 278, "cjk_mapped_from": "黒", "cjk_mapped_to": "黑"},
{"id": 279, "cjk_mapped_from": "黙", "cjk_mapped_to": "默"},
{"id": 280, "cjk_mapped_from": "齢", "cjk_mapped_to": "齡"}
]